LICENSE
README.md
setup.py
lyner/__init__.py
lyner/__main__.py
lyner/_main.py
lyner/click_extras.py
lyner/custom_distributions.py
lyner/custom_matrices.py
lyner/dendromap.py
lyner/keras_extras.py
lyner/main.py
lyner/misc.py
lyner/plotly_extras.py
lyner.egg-info/PKG-INFO
lyner.egg-info/SOURCES.txt
lyner.egg-info/dependency_links.txt
lyner.egg-info/entry_points.txt
lyner.egg-info/requires.txt
lyner.egg-info/top_level.txt
lyner/commands/__init__.py
lyner/commands/bio.py
lyner/commands/cluster.py
lyner/commands/io.py
lyner/commands/keras.py
lyner/commands/plot.py
lyner/commands/stats.py
lyner/commands/transform.py