Metadata-Version: 1.0
Name: lyner
Version: 0.4.3
Summary: A chaining toolbox for working with dataframes
Home-page: https://github.com/tedil/lyner
Author: Till Hartmann
Author-email: till.hartmann@udo.edu
License: MIT
Platform: UNKNOWN
